{
  "lines": [
    {
      "id": "01",
      "name": "Сокольническая линия"
    },
    {
      "id": "02",
      "name": "Замоскворецкая линия"
    },
    {
      "id": "03",
      "name": "Арбатско-Покровская линия"
    },
    {
      "id": "04",
      "name": "Филёвская линия"
    },
    {
      "id": "05",
      "name": "Кольцевая линия"
    },
    {
      "id": "06",
      "name": "Калужско-Рижская линия"
    },
    {
      "id": "07",
      "name": "Таганско-Краснопресненская линия"
    },
    {
      "id": "8А",
      "name": "Солнцевская линия"
    },
    {
      "id": "08",
      "name": "Калининская линия"
    },
    {
      "id": "09",
      "name": "Серпуховско-Тимирязевская линия"
    },
    {
      "id": "10",
      "name": "Люблинско-Дмитровская линия"
    },
    {
      "id": "11",
      "name": "Большая кольцевая линия"
    },
    {
      "id": "011А",
      "name": "Каховская линия"
    },
    {
      "id": "12",
      "name": "Бутовская линия"
    },
    {
      "id": "15",
      "name": "Некрасовская линия"
    }
  ],
  "stations": {
    "01": [
      "Бульвар Рокоссовского",
      "Черкизовская",
      "Преображенская площадь",
      "Сокольники",
      "Красносельская",
      "Комсомольская",
      "Красные Ворота",
      "Чистые пруды",
      "Лубянка",
      "Охотный Ряд",
      "Библиотека имени Ленина",
      "Кропоткинская",
      "Парк культуры",
      "Фрунзенская",
      "Спортивная",
      "Воробьёвы горы",
      "Университет",
      "Проспект Вернадского",
      "Юго-Западная",
      "Тропарёво",
      "Румянцево",
      "Саларьево",
      "Филатов луг",
      "Прокшино",
      "Ольховая",
      "Коммунарка"
    ],
    "011А": [
      "Каширская",
      "Варшавская",
      "Каховская"
    ],
    "02": [
      "Ховрино",
      "Беломорская",
      "Речной вокзал",
      "Водный стадион",
      "Войковская",
      "Сокол",
      "Аэропорт",
      "Динамо",
      "Белорусская",
      "Маяковская",
      "Тверская",
      "Театральная",
      "Новокузнецкая",
      "Павелецкая",
      "Автозаводская",
      "Технопарк",
      "Коломенская",
      "Каширская",
      "Кантемировская",
      "Царицыно",
      "Орехово",
      "Домодедовская",
      "Красногвардейская",
      "Алма-Атинская"
    ],
    "03": [
      "Пятницкое шоссе",
      "Митино",
      "Волоколамская",
      "Мякинино",
      "Строгино",
      "Крылатское",
      "Молодёжная",
      "Кунцевская",
      "Славянский бульвар",
      "Парк Победы",
      "Киевская",
      "Смоленская",
      "Арбатская",
      "Площадь Революции",
      "Курская",
      "Бауманская",
      "Электрозаводская",
      "Семёновская",
      "Партизанская",
      "Измайловская",
      "Первомайская",
      "Щёлковская"
    ],
    "04": [
      "Кунцевская",
      "Пионерская",
      "Филёвский парк",
      "Багратионовская",
      "Фили",
      "Кутузовская",
      "Студенческая",
      "Международная",
      "Выставочная",
      "Киевская",
      "Смоленская",
      "Арбатская",
      "Александровский сад"
    ],
    "05": [
      "Парк культуры",
      "Октябрьская",
      "Добрынинская",
      "Павелецкая",
      "Таганская",
      "Курская",
      "Комсомольская",
      "Проспект Мира",
      "Новослободская",
      "Белорусская",
      "Краснопресненская",
      "Киевская"
    ],
    "06": [
      "Медведково",
      "Бабушкинская",
      "Свиблово",
      "Ботанический сад",
      "ВДНХ",
      "Алексеевская",
      "Рижская",
      "Проспект Мира",
      "Сухаревская",
      "Тургеневская",
      "Китай-город",
      "Третьяковская",
      "Октябрьская",
      "Шаболовская",
      "Ленинский проспект",
      "Академическая",
      "Профсоюзная",
      "Новые Черёмушки",
      "Калужская",
      "Беляево",
      "Коньково",
      "Тёплый Стан",
      "Ясенево",
      "Новоясеневская"
    ],
    "07": [
      "Планерная",
      "Сходненская",
      "Тушинская",
      "Спартак",
      "Щукинская",
      "Октябрьское Поле",
      "Полежаевская",
      "Беговая",
      "Улица 1905 года",
      "Баррикадная",
      "Пушкинская",
      "Кузнецкий Мост",
      "Китай-город",
      "Таганская",
      "Пролетарская",
      "Волгоградский проспект",
      "Текстильщики",
      "Кузьминки",
      "Рязанский проспект",
      "Выхино",
      "Лермонтовский проспект",
      "Жулебино",
      "Котельники"
    ],
    "08": [
      "Третьяковская",
      "Марксистская",
      "Площадь Ильича",
      "Авиамоторная",
      "Шоссе Энтузиастов",
      "Перово",
      "Новогиреево",
      "Новокосино"
    ],
    "09": [
      "Алтуфьево",
      "Бибирево",
      "Отрадное",
      "Владыкино",
      "Петровско-Разумовская",
      "Тимирязевская",
      "Дмитровская",
      "Савёловская",
      "Менделеевская",
      "Цветной бульвар",
      "Чеховская",
      "Боровицкая",
      "Полянка",
      "Серпуховская",
      "Тульская",
      "Нагатинская",
      "Нагорная",
      "Нахимовский проспект",
      "Севастопольская",
      "Чертановская",
      "Южная",
      "Пражская",
      "Улица Академика Янгеля",
      "Аннино",
      "Бульвар Дмитрия Донского"
    ],
    "10": [
      "Селигерская",
      "Верхние Лихоборы",
      "Окружная",
      "Петровско-Разумовская",
      "Фонвизинская",
      "Бутырская",
      "Марьина Роща",
      "Достоевская",
      "Трубная",
      "Сретенский бульвар",
      "Чкаловская",
      "Римская",
      "Крестьянская застава",
      "Дубровка",
      "Кожуховская",
      "Печатники",
      "Волжская",
      "Люблино",
      "Братиславская",
      "Марьино",
      "Борисово",
      "Шипиловская",
      "Зябликово"
    ],
    "11": [
      "Деловой центр",
      "Шелепиха",
      "Хорошёвская",
      "ЦСКА",
      "Петровский парк",
      "Савёловская"
    ],
    "12": [
      "Битцевский парк",
      "Лесопарковая",
      "Улица Старокачаловская",
      "Улица Скобелевская",
      "Бульвар Адмирала Ушакова",
      "Улица Горчакова",
      "Бунинская аллея"
    ],
    "15": [
      "Косино",
      "Улица Дмитриевского",
      "Лухмановская",
      "Некрасовка"
    ],
    "8А": [
      "Рассказовка",
      "Новопеределкино",
      "Боровское шоссе",
      "Солнцево",
      "Говорово",
      "Озёрная",
      "Мичуринский проспект",
      "Раменки",
      "Ломоносовский проспект",
      "Минская",
      "Парк Победы",
      "Деловой центр",
      "Шелепиха",
      "Хорошёвская",
      "ЦСКА",
      "Петровский парк",
      "Савёловская"
    ]
  },
  "connections": [
    [
      {
        "lineId": "01",
        "name": "Бульвар Рокоссовского"
      },
      {
        "lineId": "14",
        "name": "Бульвар Рокоссовского"
      }
    ],
    [
      {
        "lineId": "02",
        "name": "Черкизовская"
      },
      {
        "lineId": "14",
        "name": "Локомотив"
      }
    ],
    [
      {
        "lineId": "06",
        "name": "Комсомольская"
      },
      {
        "lineId": "05",
        "name": "Комсомольская"
      }
    ],
    [
      {
        "lineId": "08",
        "name": "Чистые пруды"
      },
      {
        "lineId": "06",
        "name": "Тургеневская"
      },
      {
        "lineId": "10",
        "name": "Сретенский бульвар"
      }
    ],
    [
      {
        "lineId": "09",
        "name": "Лубянка"
      },
      {
        "lineId": "07",
        "name": "Кузнецкий Мост"
      }
    ],
    [
      {
        "lineId": "10",
        "name": "Охотный Ряд"
      },
      {
        "lineId": "02",
        "name": "Театральная"
      }
    ],
    [
      {
        "lineId": "11",
        "name": "Библиотека имени Ленина"
      },
      {
        "lineId": "03",
        "name": "Арбатская"
      },
      {
        "lineId": "04",
        "name": "Александровский сад"
      },
      {
        "lineId": "09",
        "name": "Боровицкая"
      }
    ],
    [
      {
        "lineId": "13",
        "name": "Парк культуры"
      },
      {
        "lineId": "05",
        "name": "Парк культуры"
      }
    ],
    [
      {
        "lineId": "15",
        "name": "Спортивная"
      },
      {
        "lineId": "14",
        "name": "Лужники Московского"
      }
    ],
    [
      {
        "lineId": "03",
        "name": "Войковская"
      },
      {
        "lineId": "14",
        "name": "Балтийская"
      }
    ],
    [
      {
        "lineId": "06",
        "name": "Динамо"
      },
      {
        "lineId": "11",
        "name": "Петровский парк"
      }
    ],
    [
      {
        "lineId": "07",
        "name": "Белорусская"
      },
      {
        "lineId": "05",
        "name": "Белорусская"
      }
    ],
    [
      {
        "lineId": "09",
        "name": "Тверская"
      },
      {
        "lineId": "07",
        "name": "Пушкинская"
      },
      {
        "lineId": "09",
        "name": "Чеховская"
      }
    ],
    [
      {
        "lineId": "10",
        "name": "Театральная"
      },
      {
        "lineId": "01",
        "name": "Охотный Ряд"
      },
      {
        "lineId": "03",
        "name": "Площадь Революции"
      }
    ],
    [
      {
        "lineId": "11",
        "name": "Новокузнецкая"
      },
      {
        "lineId": "06",
        "name": "Третьяковская"
      },
      {
        "lineId": "08",
        "name": "Третьяковская"
      }
    ],
    [
      {
        "lineId": "12",
        "name": "Павелецкая"
      },
      {
        "lineId": "05",
        "name": "Павелецкая"
      }
    ],
    [
      {
        "lineId": "13",
        "name": "Автозаводская"
      },
      {
        "lineId": "14",
        "name": "Автозаводская"
      }
    ],
    [
      {
        "lineId": "15",
        "name": "Каширская"
      },
      {
        "lineId": "011А",
        "name": "Каширская"
      }
    ],
    [
      {
        "lineId": "20",
        "name": "Красногвардейская"
      },
      {
        "lineId": "10",
        "name": "Зябликово"
      }
    ],
    [
      {
        "lineId": "08",
        "name": "Кунцевская"
      },
      {
        "lineId": "04",
        "name": "Кунцевская"
      }
    ],
    [
      {
        "lineId": "10",
        "name": "Парк Победы"
      },
      {
        "lineId": "08",
        "name": "Парк Победы"
      }
    ],
    [
      {
        "lineId": "11",
        "name": "Киевская"
      },
      {
        "lineId": "04",
        "name": "Киевская"
      },
      {
        "lineId": "05",
        "name": "Киевская"
      }
    ],
    [
      {
        "lineId": "13",
        "name": "Арбатская"
      },
      {
        "lineId": "01",
        "name": "Библиотека имени Ленина"
      },
      {
        "lineId": "04",
        "name": "Александровский сад"
      },
      {
        "lineId": "09",
        "name": "Боровицкая"
      }
    ],
    [
      {
        "lineId": "14",
        "name": "Площадь Революции"
      },
      {
        "lineId": "02",
        "name": "Театральная"
      }
    ],
    [
      {
        "lineId": "15",
        "name": "Курская"
      },
      {
        "lineId": "05",
        "name": "Курская"
      },
      {
        "lineId": "10",
        "name": "Чкаловская"
      }
    ],
    [
      {
        "lineId": "19",
        "name": "Партизанская"
      },
      {
        "lineId": "14",
        "name": "Измайлово"
      }
    ],
    [
      {
        "lineId": "01",
        "name": "Кунцевская"
      },
      {
        "lineId": "03",
        "name": "Кунцевская"
      }
    ],
    [
      {
        "lineId": "06",
        "name": "Кутузовская"
      },
      {
        "lineId": "14",
        "name": "Кутузовская"
      }
    ],
    [
      {
        "lineId": "08",
        "name": "Международная"
      },
      {
        "lineId": "14",
        "name": "Деловой центр"
      }
    ],
    [
      {
        "lineId": "09",
        "name": "Выставочная"
      },
      {
        "lineId": "08",
        "name": "Деловой центр"
      },
      {
        "lineId": "11",
        "name": "Деловой центр"
      }
    ],
    [
      {
        "lineId": "10",
        "name": "Киевская"
      },
      {
        "lineId": "03",
        "name": "Киевская"
      },
      {
        "lineId": "05",
        "name": "Киевская"
      }
    ],
    [
      {
        "lineId": "13",
        "name": "Александровский сад"
      },
      {
        "lineId": "01",
        "name": "Библиотека имени Ленина"
      },
      {
        "lineId": "03",
        "name": "Арбатская"
      }
    ],
    [
      {
        "lineId": "01",
        "name": "Парк культуры"
      },
      {
        "lineId": "01",
        "name": "Парк культуры"
      }
    ],
    [
      {
        "lineId": "02",
        "name": "Октябрьская"
      },
      {
        "lineId": "06",
        "name": "Октябрьская"
      }
    ],
    [
      {
        "lineId": "03",
        "name": "Добрынинская"
      },
      {
        "lineId": "09",
        "name": "Серпуховская"
      }
    ],
    [
      {
        "lineId": "04",
        "name": "Павелецкая"
      },
      {
        "lineId": "02",
        "name": "Павелецкая"
      }
    ],
    [
      {
        "lineId": "05",
        "name": "Таганская"
      },
      {
        "lineId": "07",
        "name": "Таганская"
      },
      {
        "lineId": "08",
        "name": "Марксистская"
      }
    ],
    [
      {
        "lineId": "06",
        "name": "Курская"
      },
      {
        "lineId": "03",
        "name": "Курская"
      },
      {
        "lineId": "10",
        "name": "Чкаловская"
      }
    ],
    [
      {
        "lineId": "07",
        "name": "Комсомольская"
      },
      {
        "lineId": "01",
        "name": "Комсомольская"
      }
    ],
    [
      {
        "lineId": "08",
        "name": "Проспект Мира"
      },
      {
        "lineId": "06",
        "name": "Проспект Мира"
      }
    ],
    [
      {
        "lineId": "09",
        "name": "Новослободская"
      },
      {
        "lineId": "09",
        "name": "Менделеевская"
      }
    ],
    [
      {
        "lineId": "10",
        "name": "Белорусская"
      },
      {
        "lineId": "02",
        "name": "Белорусская"
      }
    ],
    [
      {
        "lineId": "11",
        "name": "Краснопресненская"
      },
      {
        "lineId": "07",
        "name": "Баррикадная"
      }
    ],
    [
      {
        "lineId": "12",
        "name": "Киевская"
      },
      {
        "lineId": "03",
        "name": "Киевская"
      },
      {
        "lineId": "04",
        "name": "Киевская"
      }
    ],
    [
      {
        "lineId": "04",
        "name": "Ботанический сад"
      },
      {
        "lineId": "14",
        "name": "Ботанический сад"
      }
    ],
    [
      {
        "lineId": "05",
        "name": "ВДНХ"
      },
      {
        "lineId": "13",
        "name": "Выставочный центр"
      }
    ],
    [
      {
        "lineId": "08",
        "name": "Проспект Мира"
      },
      {
        "lineId": "05",
        "name": "Проспект Мира"
      }
    ],
    [
      {
        "lineId": "10",
        "name": "Тургеневская"
      },
      {
        "lineId": "01",
        "name": "Чистые пруды"
      },
      {
        "lineId": "10",
        "name": "Сретенский бульвар"
      }
    ],
    [
      {
        "lineId": "11",
        "name": "Китай-город"
      },
      {
        "lineId": "07",
        "name": "Китай-город"
      }
    ],
    [
      {
        "lineId": "12",
        "name": "Третьяковская"
      },
      {
        "lineId": "02",
        "name": "Новокузнецкая"
      },
      {
        "lineId": "08",
        "name": "Третьяковская"
      }
    ],
    [
      {
        "lineId": "13",
        "name": "Октябрьская"
      },
      {
        "lineId": "05",
        "name": "Октябрьская"
      }
    ],
    [
      {
        "lineId": "15",
        "name": "Ленинский проспект"
      },
      {
        "lineId": "14",
        "name": "Площадь Гагарина"
      }
    ],
    [
      {
        "lineId": "24",
        "name": "Новоясеневская"
      },
      {
        "lineId": "12",
        "name": "Битцевский парк"
      }
    ],
    [
      {
        "lineId": "06",
        "name": "Октябрьское Поле"
      },
      {
        "lineId": "14",
        "name": "Панфиловская"
      }
    ],
    [
      {
        "lineId": "07",
        "name": "Полежаевская"
      },
      {
        "lineId": "11",
        "name": "Хорошёвская Большой"
      },
      {
        "lineId": "14",
        "name": "Хорошёво"
      }
    ],
    [
      {
        "lineId": "10",
        "name": "Баррикадная"
      },
      {
        "lineId": "05",
        "name": "Краснопресненская"
      }
    ],
    [
      {
        "lineId": "11",
        "name": "Пушкинская"
      },
      {
        "lineId": "02",
        "name": "Тверская"
      },
      {
        "lineId": "09",
        "name": "Чеховская"
      }
    ],
    [
      {
        "lineId": "12",
        "name": "Кузнецкий Мост"
      },
      {
        "lineId": "01",
        "name": "Лубянка"
      }
    ],
    [
      {
        "lineId": "13",
        "name": "Китай-город"
      },
      {
        "lineId": "06",
        "name": "Китай-город"
      }
    ],
    [
      {
        "lineId": "14",
        "name": "Таганская"
      },
      {
        "lineId": "05",
        "name": "Таганская"
      },
      {
        "lineId": "08",
        "name": "Марксистская"
      }
    ],
    [
      {
        "lineId": "15",
        "name": "Пролетарская"
      },
      {
        "lineId": "10",
        "name": "Крестьянская застава"
      }
    ],
    [
      {
        "lineId": "21",
        "name": "Лермонтовский проспект"
      },
      {
        "lineId": "15",
        "name": "Косино"
      }
    ],
    [
      {
        "lineId": "04",
        "name": "Парк Победы"
      },
      {
        "lineId": "03",
        "name": "Парк Победы"
      }
    ],
    [
      {
        "lineId": "05",
        "name": "Деловой центр"
      },
      {
        "lineId": "04",
        "name": "Выставочная"
      },
      {
        "lineId": "11",
        "name": "Деловой центр"
      }
    ],
    [
      {
        "lineId": "06",
        "name": "Третьяковская"
      },
      {
        "lineId": "02",
        "name": "Новокузнецкая"
      },
      {
        "lineId": "06",
        "name": "Третьяковская"
      }
    ],
    [
      {
        "lineId": "07",
        "name": "Марксистская"
      },
      {
        "lineId": "05",
        "name": "Таганская"
      },
      {
        "lineId": "07",
        "name": "Таганская"
      }
    ],
    [
      {
        "lineId": "08",
        "name": "Площадь Ильича"
      },
      {
        "lineId": "10",
        "name": "Римская"
      }
    ],
    [
      {
        "lineId": "10",
        "name": "Шоссе Энтузиастов"
      },
      {
        "lineId": "14",
        "name": "Шоссе Энтузиастов"
      }
    ],
    [
      {
        "lineId": "04",
        "name": "Владыкино"
      },
      {
        "lineId": "14",
        "name": "Владыкино"
      }
    ],
    [
      {
        "lineId": "05",
        "name": "Петровско-Разумовская"
      },
      {
        "lineId": "10",
        "name": "Петровско-Разумовская"
      }
    ],
    [
      {
        "lineId": "06",
        "name": "Тимирязевская"
      },
      {
        "lineId": "13",
        "name": "Тимирязевская"
      }
    ],
    [
      {
        "lineId": "09",
        "name": "Менделеевская"
      },
      {
        "lineId": "05",
        "name": "Новослободская"
      }
    ],
    [
      {
        "lineId": "10",
        "name": "Цветной бульвар"
      },
      {
        "lineId": "10",
        "name": "Трубная"
      }
    ],
    [
      {
        "lineId": "11",
        "name": "Чеховская"
      },
      {
        "lineId": "02",
        "name": "Тверская"
      },
      {
        "lineId": "07",
        "name": "Пушкинская"
      }
    ],
    [
      {
        "lineId": "12",
        "name": "Боровицкая"
      },
      {
        "lineId": "01",
        "name": "Библиотека имени Ленина"
      },
      {
        "lineId": "03",
        "name": "Арбатская"
      }
    ],
    [
      {
        "lineId": "14",
        "name": "Серпуховская"
      },
      {
        "lineId": "05",
        "name": "Добрынинская"
      }
    ],
    [
      {
        "lineId": "16",
        "name": "Нагатинская"
      },
      {
        "lineId": "14",
        "name": "Верхние Котлы"
      }
    ],
    [
      {
        "lineId": "19",
        "name": "Севастопольская"
      },
      {
        "lineId": "011А",
        "name": "Каховская"
      }
    ],
    [
      {
        "lineId": "25",
        "name": "Бульвар Дмитрия Донского"
      },
      {
        "lineId": "12",
        "name": "Улица Старокачаловская"
      }
    ],
    [
      {
        "lineId": "01",
        "name": "Окружная"
      },
      {
        "lineId": "14",
        "name": "Окружная"
      }
    ],
    [
      {
        "lineId": "01",
        "name": "Петровско-Разумовская"
      },
      {
        "lineId": "09",
        "name": "Петровско-Разумовская"
      }
    ],
    [
      {
        "lineId": "02",
        "name": "Фонвизинская"
      },
      {
        "lineId": "13",
        "name": "Улица Милашенкова Московского монорельса"
      }
    ],
    [
      {
        "lineId": "06",
        "name": "Трубная"
      },
      {
        "lineId": "09",
        "name": "Цветной бульвар"
      }
    ],
    [
      {
        "lineId": "07",
        "name": "Сретенский бульвар"
      },
      {
        "lineId": "01",
        "name": "Чистые пруды"
      },
      {
        "lineId": "06",
        "name": "Тургеневская"
      }
    ],
    [
      {
        "lineId": "08",
        "name": "Чкаловская"
      },
      {
        "lineId": "03",
        "name": "Курская"
      },
      {
        "lineId": "05",
        "name": "Курская"
      }
    ],
    [
      {
        "lineId": "09",
        "name": "Римская"
      },
      {
        "lineId": "08",
        "name": "Площадь Ильича"
      }
    ],
    [
      {
        "lineId": "10",
        "name": "Крестьянская застава"
      },
      {
        "lineId": "07",
        "name": "Пролетарская"
      }
    ],
    [
      {
        "lineId": "11",
        "name": "Дубровка"
      },
      {
        "lineId": "14",
        "name": "Дубровка"
      }
    ],
    [
      {
        "lineId": "20",
        "name": "Зябликово"
      },
      {
        "lineId": "02",
        "name": "Красногвардейская"
      }
    ],
    [
      {
        "lineId": "01",
        "name": "Деловой центр"
      },
      {
        "lineId": "04",
        "name": "Выставочная"
      },
      {
        "lineId": "8А",
        "name": "Деловой центр"
      }
    ],
    [
      {
        "lineId": "11",
        "name": "Шелепиха"
      },
      {
        "lineId": "14",
        "name": "Шелепиха"
      }
    ],
    [
      {
        "lineId": "11",
        "name": "Хорошёвская"
      },
      {
        "lineId": "07",
        "name": "Полежаевская"
      },
      {
        "lineId": "14",
        "name": "Хорошёво"
      }
    ],
    [
      {
        "lineId": "11",
        "name": "Петровский парк"
      },
      {
        "lineId": "02",
        "name": "Динамо"
      }
    ],
    [
      {
        "lineId": "11",
        "name": "Савёловская"
      },
      {
        "lineId": "09",
        "name": "Савёловская"
      }
    ],
    [
      {
        "lineId": "01",
        "name": "Каширская"
      },
      {
        "lineId": "02",
        "name": "Каширская"
      }
    ],
    [
      {
        "lineId": "03",
        "name": "Каховская"
      },
      {
        "lineId": "09",
        "name": "Севастопольская"
      }
    ],
    [
      {
        "lineId": "01",
        "name": "Битцевский парк"
      },
      {
        "lineId": "06",
        "name": "Новоясеневская"
      }
    ],
    [
      {
        "lineId": "03",
        "name": "Улица Старокачаловская"
      },
      {
        "lineId": "09",
        "name": "Бульвар Дмитрия Донского"
      }
    ],
    [
      {
        "lineId": "01",
        "name": "Косино"
      },
      {
        "lineId": "07",
        "name": "Лермонтовский проспект"
      }
    ]
  ]
}